Workbook

Sheet Cover Page
A1: Republic of the Philippines Provincial Government of Batangas PROVINCIAL HEALTH OFFICE Brgy. Kumintang Ibaba, Batangas City E-mail: pho@batangas.gov.ph | Tel No. (043) 740-2832; (043) 723-2592
A2: PROJECT PROCUREMENT MANAGEMENT PLAN 2025
A3: END USER/UNIT: | C3: PROVINCIAL HEALTH OFFICE - PROPER
A4: CHARGED TO: | C4: GENERAL FUND - PHO - PROPER
A6: ACCOUNT CODE | C6: ACCOUNT NAME | D6: AMOUNT
A7: ='PHO-PROPER FUND'!A10 -> 50201010 | C7: TRAVELING EXPENSES - LOCAL | D7: =#REF! -> #REF!
A8: 50202010 | C8: TRAINING EXPENSES | D8: =#REF! -> #REF!
A9: 50203010 | C9: OFFICE SUPPLIES EXPENSES | D9: =#REF! -> #REF!
A10: 50203020 | C10: ACCOUNTABLE FORMS EXPENSES | D10: =#REF! -> #REF!
A11: 50203030 | C11: NON-ACCOUNTABLE FORMS EXPENSES | D11: ='PHO-PROPER FUND'!H14 -> 475000
A12: 50203070 | C12: DRUGS AND MEDICINES EXPENSES | D12: ='PHO-PROPER FUND'!H354 -> 28500000
A13: 50203080 | C13: MEDICAL, DENTAL, LABORATORY SUPPLIES EXPENSES | D13: ='PHO-PROPER FUND'!H568 -> 28500000
A14: 50203090 | C14: FUEL, OIL AND LUBRICANTS EXPENSES | D14: ='PHO-PROPER FUND'!H16 -> 3500000
A15: 50203990 | C15: OTHER SUPPLIES AND MATERIALS EXPENSES | D15: ='PHO-PROPER FUND'!H871 -> 1700000
C16: WATER EXPENSES | D16: =0 -> 0
C17: ELECTRICITY EXPENSES | D17: =0 -> 0
C18: CABLE, SATELLITE, TELEGRAPH AND RADIO EXPENSES | D18: ='PHO-PROPER FUND'!H22 -> 20000
A19: 50206020 | C19: PRIZES | D19: ='PHO-PROPER FUND'!H24 -> 210000
A20: 50213040 | C20: REPAIRS AND MAINTENANCE - BUILDING AND OTHER STRUCTURES | D20: ='PHO-PROPER FUND'!H27 -> 3200000
A21: 50213050 | C21: REPAIRS AND MAINTENANCE - MACHINERY AND EQUIPMENT | D21: ='PHO-PROPER FUND'!H29 -> 400000
A22: 50213060 | C22: REPAIRS AND MAINTENANCE - TRANSPORTATION EQUIPMENT | D22: ='PHO-PROPER FUND'!H31 -> 750000
C23: TAXES, DUTIES AND LICENSES | D23: ='PHO-PROPER FUND'!#REF! -> #ERROR!
C24: FIDELITY BOND PREMIUMS | D24: ='PHO-PROPER FUND'!#REF! -> #ERROR!
A25: 50299020 | C25: PRINTING AND PUBLICATION EXPENSES
A26: 50299030 | C26: REPRESENTATION EXPENSES
C27: TRANSPORTATION & DELIVERY EXPENSES | D27: ='PHO-PROPER FUND'!H39 -> 260000
C28: RENT EXPENSES
C29: SUBSCRIPTION EXPENSES
A30: 50299990 | C30: OTHER MAINTENANCE AND OPERATING EXPENSES
A31: 10704990 | C31: CAPITAL OUTLAY - OTHER STRUCTURES
A32: 10705010 | C32: CAPITAL OUTLAY - MACHINERY
A33: 10705020 | C33: CAPITAL OUTLAY - OFFICE EQUIPMENT
A34: 10705030 | C34: CAPITAL OUTLAY - INFORMATION AND COMMUNICATION TECHNOLOGY EQUIPMENT
A35: 10705070 | C35: CAPITAL OUTLAY - COMMUNICATION EQUIPMENT
A36: 10705110 | C36: CAPITAL OUTLAY - MEDICAL EQUIPMENT
A37: 10707010 | C37: CAPITAL OUTLAY - FURNITURE AND FIXTURES
A38: 50203130 | C38: CHEMICAL AND FILTERING SUPPLIES EXPENSE
A39: 50211030 | C39: CONSULTANCY SERVICES
A40: 50212010 | C40: ENVIRONMENTAL AND SANITARY SERVICES
A41: 50299080 | C41: DONATIONS
C43: GRAND TOTAL | D43: =SUM(D7:D41) -> #REF!

Sheet PHO-PROPER GEN. FUND
A1: Republic of the Philippines Provincial Government of Batangas PROVINCIAL HEALTH OFFICE Brgy. Kumintang Ibaba, Batangas City E-mail: pho@batangas.gov.ph | Tel No. (043) 740-2832; (043) 723-2592
A2: PROJECT PROCUREMENT MANAGEMENT PLAN 2026
A3: END USER/UNIT: | C3: PROVINCIAL HEALTH OFFICE - PROPER
A4: CHARGED TO: | C4: GENERAL FUND - PHO-PROPER
A6: CODE | B6: GENERAL DESCRIPTION | E6: QTY | F6: UNIT | G6: UNIT PRICE | H6: ESTIMATED BUDGET | I6: MODE OF PROCUREMENT | J6: SCHEDULE / MILESTONE OF ACTIVITIES
J7: JAN | K7: FEB | L7: MAR | M7: APR | N7: MAY | O7: JUN | P7: JUL | Q7: AUG | R7: SEP | S7: OCT | T7: NOV | U7: DEC
C8: MAINTENANCE AND OTHER OPERATING EXPENSES
A10: 50201010 | C10: TRAVELING EXPENSES - LOCAL | H10: 2000000 | J10: x | K10: x | L10: x | M10: x | N10: x | O10: x | P10: x | Q10: x | R10: x | S10: x | T10: x | U10: x
A12: ='Cover Page'!A10 -> 50203020 | C12: ACCOUNTABLE FORMS EXPENSES | H12: 10000 | I12: BIDDING/SMALL VALUE | J12: x | K12: x | L12: x | M12: x | N12: x | O12: x | P12: x | Q12: x | R12: x | S12: x | T12: x | U12: x
C13: General Form No. 51-A (Official Receipt)
A15: ='Cover Page'!A11 -> 50203030 | C15: NON-ACCOUNTABLE FORMS EXPENSES | H15: 75000 | I15: BIDDING/SMALL VALUE | J15: x | K15: x | L15: x | M15: x | N15: x | O15: x | P15: x | Q15: x | R15: x | S15: x | T15: x | U15: x
C16: Medical/Treatment/Vaccination Forms
A18: ='Cover Page'!A14 -> 50203090 | C18: FUEL, OIL AND LUBRICANTS EXPENSES | H18: 3500000 | I18: BIDDING/SMALL VALUE | J18: x | K18: x | L18: x | M18: x | N18: x | O18: x | P18: x | Q18: x | R18: x | S18: x | T18: x | U18: x
A20: 50204010 | C20: WATER EXPENSES | H20: 10000000 | J20: x | K20: x | L20: x | M20: x | N20: x | O20: x | P20: x | Q20: x | R20: x | S20: x | T20: x | U20: x
A22: 50204020 | C22: ELECTRICITY EXPENSES | H22: 50000000 | J22: x | K22: x | L22: x | M22: x | N22: x | O22: x | P22: x | Q22: x | R22: x | S22: x | T22: x | U22: x
A24: 50205020 | C24: TELEPHONE EXPENSES | H24: 316000 | J24: x | K24: x | L24: x | M24: x | N24: x | O24: x | P24: x | Q24: x | R24: x | S24: x | T24: x | U24: x
A26: 50205030 | C26: INTERNET SUBSCRIPTION EXPENSES | H26: 300000 | J26: x | K26: x | L26: x | M26: x | N26: x | O26: x | P26: x | Q26: x | R26: x | S26: x | T26: x | U26: x
A28: 50205040 | C28: CABLE, SATELLITE, TELEGRAPH AND RADIO EXPENSES | H28: 20000 | J28: x | K28: x | L28: x | M28: x | N28: x | O28: x | P28: x | Q28: x | R28: x | S28: x | T28: x | U28: x
A30: ='Cover Page'!A19 -> 50206020 | C30: PRIZES | H30: 210000 | J30: x | K30: x | L30: x | M30: x | N30: x | O30: x | P30: x | Q30: x | R30: x | S30: x | T30: x | U30: x
C31: REPAIRS AND MAINTENANCE
A32: ='Cover Page'!A20 -> 50213040 | C32: BUILDING AND OTHER STRUCTURES | H32: 1600000 | I32: BIDDING/SMALL VALUE | J32: x | K32: x | L32: x | M32: x | N32: x | O32: x | P32: x | Q32: x | R32: x | S32: x | T32: x | U32: x
A34: ='Cover Page'!A21 -> 50213050 | C34: MACHINERY AND EQUIPMENT | H34: 900000 | I34: BIDDING/SMALL VALUE | J34: x | K34: x | L34: x | M34: x | N34: x | O34: x | P34: x | Q34: x | R34: x | S34: x | T34: x | U34: x
A36: ='Cover Page'!A22 -> 50213060 | C36: TRANSPORTATION EQUIPMENT | H36: 950000 | I36: BIDDING/SMALL VALUE | J36: x | K36: x | L36: x | M36: x | N36: x | O36: x | P36: x | Q36: x | R36: x | S36: x | T36: x | U36: x
A38: 50213210 | C38: SEMI-EXPENDABLE MACHINERY AND EQUIPMENT | H38: 100000 | I38: BIDDING/SMALL VALUE | J38: x | K38: x | L38: x | M38: x | N38: x | O38: x | P38: x | Q38: x | R38: x | S38: x | T38: x | U38: x
A40: 50216010 | C40: TAXES, DUTIES, AND LICENSES | H40: 25000 | J40: x | K40: x | L40: x | M40: x | N40: x | O40: x | P40: x | Q40: x | R40: x | S40: x | T40: x | U40: x
A42: 50216020 | C42: FIDELITY BOND PREMIUMS | H42: 100000 | J42: x | K42: x | L42: x | M42: x | N42: x | O42: x | P42: x | Q42: x | R42: x | S42: x | T42: x | U42: x
A44: 50299020 | C44: PRINTING AND PUBLICATION EXPENSES | H44: 150000 | I44: BIDDING/SMALL VALUE | J44: x | K44: x | L44: x | M44: x | N44: x | O44: x | P44: x | Q44: x | R44: x | S44: x | T44: x | U44: x
C45: Posters, flyers, and other IEC materials
C46: Immunization/Vaccination/Treatment/Other Medical Cards
C47: Leaflets, pamphlets
C48: Blood Donor's ID Card
A50: 50299040 | C50: TRANSPORTATION & DELIVERY EXPENSES | H50: 160000 | I50: BIDDING/SMALL VALUE | J50: x | K50: x | L50: x | M50: x | N50: x | O50: x | P50: x | Q50: x | R50: x | S50: x | T50: x | U50: x
A52: ='Cover Page'!A8 -> 50202010 | C52: TRAINING EXPENSES | H52: 250000 | I52: BIDDING/SMALL VALUE | J52: x | K52: x | L52: x | M52: x | N52: x | O52: x | P52: x | Q52: x | R52: x | S52: x | T52: x | U52: x
C53: Meals and Accomodation/ Food and Venue
C54: Training Materials
A56: 50203010 | C56: OFFICE SUPPLIES EXPENSES | H56: 3000000 | I56: BIDDING/SMALL VALUE
C57: All Purpose Sticker A4 10's/pack | E57: 100 | F57: pack | G57: 77 | H57: =E57*G57 -> 7700 | K57: =E57/2 -> 50 | P57: =E57/2 -> 50
C58: AntiVirus Software With 2 years License | E58: 32 | F58: piece | G58: 4000 | H58: =E58*G58 -> 128000 | K58: =E58/2 -> 16 | P58: =E58/2 -> 16
C59: Arch File Vertical, 2-Ring Binder, 2" Side, Long, Black | E59: 50 | F59: piece | G59: 200 | H59: =E59*G59 -> 10000 | K59: =E59/2 -> 25 | P59: =E59/2 -> 25
C60: Arch File Vertical, 2-Ring Binder, 2" Side, A4, Black | E60: 30 | F60: piece | G60: 200 | H60: =E60*G60 -> 6000 | K60: =E60/2 -> 15 | P60: =E60/2 -> 15
C61: Ballpen Black 0.7mm | E61: 1000 | F61: piece | G61: 11.2 | H61: =E61*G61 -> 11200 | K61: =E61/2 -> 500 | P61: =E61/2 -> 500
C62: Ballpen Blue 0.7mm | E62: 1000 | F62: piece | G62: 11.2 | H62: =E62*G62 -> 11200 | K62: =E62/2 -> 500 | P62: =E62/2 -> 500
C63: Ballpen Red 0.7mm | E63: 1000 | F63: piece | G63: 11.2 | H63: =E63*G63 -> 11200 | K63: =E63/2 -> 500 | P63: =E63/2 -> 500
C64: Battery AA (4piece/pack) | E64: 100 | F64: pack | G64: 191.8 | H64: =E64*G64 -> 19180 | K64: =E64/2 -> 50 | P64: =E64/2 -> 50
C65: Battery AAA (4piece/pack) | E65: 100 | F65: pack | G65: 229.25 | H65: =E65*G65 -> 22925 | K65: =E65/2 -> 50 | P65: =E65/2 -> 50
C66: Battery AA (4piece/pack) Rechargeable with charger | E66: 20 | F66: pack | G66: 1141 | H66: =E66*G66 -> 22820 | K66: =E66/2 -> 10 | P66: =E66/2 -> 10
C67: Battery AAA (4piece/pack) Rechargeable with charger | E67: 20 | F67: pack | G67: 1159.2 | H67: =E67*G67 -> 23184 | K67: =E67/2 -> 10 | P67: =E67/2 -> 10
C68: Binder clip 2 in 12 piece per box | E68: 25 | F68: box | G68: 84 | H68: =E68*G68 -> 2100 | K68: =E68/2 -> 12.5 | P68: 12
C69: Binder clip 3/4 12 piece per box | E69: 50 | F69: box | G69: 134.4 | H69: =E69*G69 -> 6720 | K69: =E69/2 -> 25 | P69: =E69/2 -> 25
C70: Binder clip 1 5/8 12 piece per box | E70: 50 | F70: box | G70: 67.2 | H70: =E70*G70 -> 3360 | K70: =E70/2 -> 25 | P70: =E70/2 -> 25
C71: Binder clip 1 1/4 12 piece per box | E71: 50 | F71: box | G71: 100.8 | H71: =E71*G71 -> 5040 | K71: =E71/2 -> 25 | P71: =E71/2 -> 25
C72: Bond Paper White Short 80 gsm / 24 substance | E72: 300 | F72: ream | G72: 438.2 | H72: =E72*G72 -> 131460 | K72: =E72/2 -> 150 | P72: =E72/2 -> 150
C73: Bond Paper White Long 80 gsm / 24 substance | E73: 300 | F73: ream | G73: 575.4 | H73: =E73*G73 -> 172620 | K73: =E73/2 -> 150 | P73: =E73/2 -> 150
C74: Bond Paper White A4 80 gsm / 24 substance | E74: 300 | F74: ream | G74: 506.8 | H74: =E74*G74 -> 152040 | K74: =E74/2 -> 150 | P74: =E74/2 -> 150
C75: Brown Envelope Short 150LBS | E75: 1000 | F75: piece | G75: 6 | H75: =E75*G75 -> 6000 | K75: =E75/2 -> 500 | P75: =E75/2 -> 500
C76: Brown Envelope Long 150LBS | E76: 1000 | F76: piece | G76: 7 | H76: =E76*G76 -> 7000 | K76: =E76/2 -> 500 | P76: =E76/2 -> 500
C77: Bundy Clock Ribbon | E77: 12 | F77: piece | G77: 1260 | H77: =E77*G77 -> 15120 | K77: =E77/2 -> 6 | P77: =E77/2 -> 6
C78: Cable clip 100's | E78: 12 | F78: pack | G78: 7 | H78: =E78*G78 -> 84 | K78: =E78/2 -> 6 | P78: =E78/2 -> 6
C79: Calculator 12 digits (Heavy Duty) | E79: 24 | F79: piece | G79: 812.5 | H79: =E79*G79 -> 19500 | K79: =E79/2 -> 12 | P79: =E79/2 -> 12
C80: Cartolina Assorted Color (20 pieces/pack) | E80: 60 | F80: pack | G80: 100 | H80: =E80*G80 -> 6000 | K80: =E80/2 -> 30 | P80: =E80/2 -> 30
... C87: Columnar Book No. 707 | E87: 20 | F87: piece | G87: 86.25 | H87: =E87*G87 -> 1725 | K87: =E87/2 -> 10 | P87: =E87/2 -> 10
C88: Computer Keyboard Wired (USB connection) | E88: 7 | F88: unit | G88: 1000 | H88: =E88*G88 -> 7000 | K88: =E88/2 -> 3.5 | P88: 2
C89: Computer Keyboard Wireless | E89: 7 | F89: unit | G89: 1925 | H89: =E89*G89 -> 13475 | K89: =E89/2 -> 3.5 | P89: 2
C90: Computer Mouse Wireless | E90: 10 | F90: unit | G90: 945 | H90: =E90*G90 -> 9450 | K90: =E90/2 -> 5 | P90: =E90/2 -> 5
C91: Cord Nylon Fancy Yarn | E91: 10 | F91: roll | G91: 210 | H91: =E91*G91 -> 2100 | K91: =E91/2 -> 5 | P91: =E91/2 -> 5
C92: Cork Board With aluminum frame 11''x16'' | E92: 12 | F92: piece | G92: 350 | H92: =E92*G92 -> 4200 | K92: =E92/2 -> 6 | P92: =E92/2 -> 6
C93: Cork Board With aluminum frame 12"x12" | E93: 12 | F93: piece | G93: 167.5 | H93: =E93*G93 -> 2010 | K93: =E93/2 -> 6 | P93: =E93/2 -> 6
C94: Cork Board with aluminum frame 48''x60'' | E94: 8 | F94: piece | G94: 448 | H94: =E94*G94 -> 3584 | K94: =E94/2 -> 4 | P94: =E94/2 -> 4
C95: Cork Board with aluminum frame 24''x36'' | E95: 3 | F95: piece | G95: 1050.7 | H95: =E95*G95 -> 3152.1 | K95: =E95/2 -> 1.5 | P95: 1
C96: Cork Pin 100's | E96: 30 | F96: box | G96: 84 | H96: =E96*G96 -> 2520 | K96: =E96/2 -> 15 | P96: =E96/2 -> 15
C97: Correction Tape | E97: 150 | F97: piece | G97: 50 | H97: =E97*G97 -> 7500 | K97: =E97/2 -> 75 | P97: =E97/2 -> 75
C98: Colored Paper 100 piece/pack | E98: 100 | F98: pack | G98: =300*1.4 -> 420 | H98: =E98*G98 -> 42000 | K98: =E98/2 -> 50 | P98: =E98/2 -> 50
C99: Cutter Big (Heavy Duty) | E99: 20 | F99: piece | G99: 90 | H99: =E99*G99 -> 1800 | K99: =E99/2 -> 10 | P99: =E99/2 -> 10
C100: Daily Time Record (DTR) Time Card | E100: 400 | F100: piece | G100: 7 | H100: =E100*G100 -> 2800 | K100: =E100/2 -> 200 | P100: =E100/2 -> 200
C101: Dater Stamp Month/Day/Year format | E101: 5 | F101: piece | G101: 1200 | H101: =E101*G101 -> 6000 | K101: =E101/2 -> 2.5 | P101: 2
C102: Desk Organizer 3 layer mesh metal tray | E102: 5 | F102: piece | G102: 308 | H102: =E102*G102 -> 1540 | K102: =E102/2 -> 2.5 | P102: 2
C103: Desk Organizer With Mesh File Holder, Heavy Duty | E103: 7 | F103: piece | G103: 3500 | H103: =E103*G103 -> 24500 | K103: =E103/2 -> 3.5 | P103: 3
C104: Double Adhesive Tape 1'' | E104: 20 | F104: roll | G104: 39.2 | H104: =E104*G104 -> 784 | K104: =E104/2 -> 10 | P104: =E104/2 -> 10
C105: Double Adhesive Tape 2'' | E105: 20 | F105: roll | G105: 70 | H105: =E105*G105 -> 1400 | K105: =E105/2 -> 10 | P105: =E105/2 -> 10
C106: Duplicator Machine Master Roll DP-G325 | E106: 3 | F106: roll | G106: 8242.5 | H106: =E106*G106 -> 24727.5 | K106: =E106/2 -> 1.5 | P106: 1
C107: Duplicator Machine Master Roll CV/B4 UA | E107: 3 | F107: roll | G107: 8242.5 | H107: =E107*G107 -> 24727.5 | K107: =E107/2 -> 1.5 | P107: 1
C108: Duplicator Machine Toner Black Ink (DP-G325) | E108: 3 | F108: piece | G108: 11795 | H108: =E108*G108 -> 35385 | K108: =E108/2 -> 1.5 | P108: 1
C109: Duplicator Machine Toner Black Ink (CV-3230) | E109: 3 | F109: roll | G109: 11795 | H109: =E109*G109 -> 35385 | K109: =E109/2 -> 1.5 | P109: 1
C110: Eraser Rubber (medium) | E110: 20 | F110: piece | G110: 30 | H110: =E110*G110 -> 600 | K110: =E110/2 -> 10 | P110: =E110/2 -> 10
C111: Eraser WhiteBoard | E111: 5 | F111: piece | G111: 50 | H111: =E111*G111 -> 250 | K111: =E111/2 -> 2.5 | P111: 2
C112: Fastener Metal (50sets/box) | E112: 50 | F112: box | G112: 123.75 | H112: =E112*G112 -> 6187.5 | K112: =E112/2 -> 25 | P112: =E112/2 -> 25
C113: Fastener Plastic (50sets/box) | E113: 50 | F113: box | G113: 107.5 | H113: =E113*G113 -> 5375 | K113: =E113/2 -> 25 | P113: =E113/2 -> 25
C114: Filing Tray 3 layers (Metal) | E114: 60 | F114: piece | G114: 658 | H114: =E114*G114 -> 39480 | K114: =E114/2 -> 30 | P114: =E114/2 -> 30
C115: Folder Short (white) | E115: 300 | F115: piece | G115: 15 | H115: =E115*G115 -> 4500 | K115: =E115/2 -> 150 | P115: =E115/2 -> 150
C116: Folder Long (white) | E116: 600 | F116: piece | G116: 15 | H116: =E116*G116 -> 9000 | K116: =E116/2 -> 300 | P116: =E116/2 -> 300
C117: Folder Expandable Long (Green) | E117: 200 | F117: piece | G117: 42 | H117: =E117*G117 -> 8400 | K117: =E117/2 -> 100 | P117: =E117/2 -> 100
C118: Folder Pressboard Long(green) | E118: 100 | F118: piece | G118: 36 | H118: =E118*G118 -> 3600 | K118: =E118/2 -> 50 | P118: =E118/2 -> 50
C119: Gel Pen Eraseable, 0.4mm Black 12 pieces/box | E119: 60 | F119: box | G119: 100 | H119: =E119*G119 -> 6000 | K119: =E119/2 -> 30 | P119: =E119/2 -> 30
C120: Glue All Purpose 60 ml | E120: 60 | F120: piece | G120: 50.4 | H120: =E120*G120 -> 3024 | K120: =E120/2 -> 30 | P120: =E120/2 -> 30
C121: Glue Gun Heavy Duty | E121: 5 | F121: piece | G121: 387.8 | H121: =E121*G121 -> 1939 | K121: =E121/2 -> 2.5 | P121: 2
C122: Highlighter Pen Assorted Color (4piece/pack) | E122: 50 | F122: pack | G122: 210 | H122: =E122*G122 -> 10500 | K122: =E122/2 -> 25 | P122: =E122/2 -> 25
C123: Illustration Board 1 whole 30"x40" | E123: 10 | F123: piece | G123: =2250/25 -> 90 | H123: =E123*G123 -> 900 | K123: =E123/2 -> 5 | P123: =E123/2 -> 5
C124: Laminating Sheet Size A4 150microns (100/pack) | E124: 25 | F124: pack | G124: 1500.8 | H124: =E124*G124 -> 37520 | K124: =E124/2 -> 12.5 | P124: 12
C125: Laminating Sheet Size Long 150microns (100/pack) | E125: 25 | F125: pack | G125: 1841 | H125: =E125*G125 -> 46025 | K125: =E125/2 -> 12.5 | P125: 12
C126: Manila paper 36''x48'' (10 pieces/pack) | E126: 50 | F126: pack | G126: 72 | H126: =E126*G126 -> 3600 | K126: =E126/2 -> 25 | P126: =E126/2 -> 25
...

Sheet ISVWP FUND
A1: Republic of the Philippines Provincial Government of Batangas PROVINCIAL HEALTH OFFICE Brgy. Kumintang Ibaba, Batangas City E-mail: pho@batangas.gov.ph | Tel No. (043) 740-2832; (043) 723-2592
A2: PROJECT PROCUREMENT MANAGEMENT PLAN 2026
A3: END USER/UNIT: | C3: PROVINCIAL HEALTH OFFICE
A4: CHARGED TO: | C4: INTEGRATED SERVICE VOLUNTEER WORKERS PROGRAM
A6: CODE | B6: GENERAL DESCRIPTION | E6: QTY | F6: UNIT | G6: UNIT PRICE | H6: ESTIMATED BUDGET | I6: MODE OF PROCUREMENT | J6: SCHEDULE / MILESTONE OF ACTIVITIES
J7: JAN | K7: FEB | L7: MAR | M7: APR | N7: MAY | O7: JUN | P7: JUL | Q7: AUG | R7: SEP | S7: OCT | T7: NOV | U7: DEC
C8: MAINTENANCE AND OTHER OPERATING EXPENSES
A10: 50299080 | C10: DONATIONS | H10: 101420000
C11: Honorarium of Volunteer Workers
C12: -Barangay Health Workers | H12: 72000000 | L12: x | O12: x | R12: x | U12: x
C13: -Barangay Nutrition Scholars | H13: 18000000 | L13: x | O13: x | R13: x | U13: x
C16: Additional Incentives for BHW and BNS Presidents | H16: 852000 | L16: x | O16: x | R16: x | U16: x
C18: Cash Incentive for Provincial Service Incentive (PSI) applicants - retired BHWs and BNSs | H18: 815400 | J18: x | K18: x | L18: x | M18: x | N18: x | O18: x | P18: x | Q18: x | R18: x | S18: x | T18: x | U18: x
C20: T shirt for BHWs and BNS | H20: 3750000 | I20: BIDDING | L20: x
C21: Transportation Allowance of BHWs and BNSs | H21: 6000000 | L21: x | O21: x | R21: x | U21: x
E23: GRAND TOTAL | H23: =SUM(H12:H21) -> 101417400
A27: Prepared by: | F27: Recommending Approval: | P27: Approved by:
A31: CYNTHIA E. LACABA | F31: GERALD G. ALDAY, MD., MPA., FPSMSI | P31: HON. VILMA SANTOS RECTO
A32: Nutrition Officer IV | F32: OIC - Provincial Health Officer | P32: Provincial Governor

Sheet CAPITAL OUTLAY
A1: Republic of the Philippines Provincial Government of Batangas PROVINCIAL HEALTH OFFICE Brgy. Kumintang Ibaba, Batangas City E-mail: pho@batangas.gov.ph | Tel No. (043) 740-2832; (043) 723-2592
A2: PROJECT PROCUREMENT MANAGEMENT PLAN 2025
A3: END USER/UNIT: | C3: PROVINCIAL HEALTH OFFICE - PROPER
A4: CHARGED TO: | C4: GENERAL FUND - PHO-PROPER
A6: CODE | B6: GENERAL DESCRIPTION | E6: QTY | F6: UNIT | G6: UNIT PRICE | H6: ESTIMATED BUDGET | I6: MODE OF PROCUREMENT | J6: SCHEDULE / MILESTONE OF ACTIVITIES
J7: JAN | K7: FEB | L7: MAR | M7: APR | N7: MAY | O7: JUN | P7: JUL | Q7: AUG | R7: SEP | S7: OCT | T7: NOV | U7: DEC
C8: CAPITAL OUTLAY
A10: 10705010 | C10: MACHINERY | H10: 3000000 | I10: BIDDING/SHOPPING/ SMALL VALUE
C11: Washing Machine | D11: 15.0kg Digital Inverter, Fully Automatic Top Load | E11: 10 | F11: unit | G11: 50200 | H11: =E11*G11 -> 502000
C12: Dryer Industrial Type | D12: 9 kg | E12: 5 | F12: unit | G12: 59000 | H12: =E12*G12 -> 295000
C13: Floor Polisher | D13: Industrial Type, Wet and Dry | E13: 6 | F13: unit | G13: 50600 | H13: =E13*G13 -> 303600
C14: Food Conveyor | D14: With Trays, 2-doors, stainless, 30 trays capacity | E14: 14 | F14: unit | G14: 85000 | H14: =E14*G14 -> 1190000
C15: Sound System | E15: 1 | F15: unit | G15: 52000 | H15: =E15*G15 -> 52000
C16: Steamer | D16: for laundry | E16: 1 | F16: unit | G16: 60000 | H16: =E16*G16 -> 60000
C17: Dish Sterilizer | D17: HDS 88 CUFT | E17: 1 | F17: unit | G17: 50100 | H17: =E17*G17 -> 50100
C18: Refrigerator | D18: 2-Door, Inverter | E18: 4 | F18: unit | G18: 56000 | H18: =E18*G18 -> 224000
C20: Total | H20: =SUM(H11:H19) -> 2676700
C22: For use of Provincial Health Care Facility | G22: =SUM(H23) -> 50000 | I22: BIDDING/SHOPPING/ SMALL VALUE
C23: Airconditioning Unit | D23: 2 HP Window Type (Inverter) | E23: 2 | F23: unit | G23: 25000 | H23: =E23*G23 -> 50000 | K23: =E23 -> 2
C25: For use of Apacible Memorial District Hospital | G25: =SUM(H26:H33) -> 519000 | I25: BIDDING/SHOPPING/ SMALL VALUE
C26: 15.0kg Digital Inverter, Fully Automatic Top Load Washing Machine | D26: Washer Type:Top Load Capacity:15.0 kg Spin Speed:700 rpm Pulsator:PP Dual Storm Voltage/Frequency: 230V/60Hz Gross Weight: 45.0 kg Net Weight: 41.0 kg Gross Dimensions (WxHxD) : 660 x 1165 x 740 mm Net Dimensions (WxHxD) : 610 x 1089 x 675 mm | E26: 2 | F26: unit | G26: 20000 | H26: =E26*G26 -> 40000 | K26: =E26 -> 2
C27: Ceiling Fan | E27: 10 | F27: unit | G27: 3000 | H27: =E27*G27 -> 30000 | K27: =E27 -> 10
C28: Stand Fan | E28: 5 | F28: unit | G28: 3000 | H28: =E28*G28 -> 15000 | K28: =E28 -> 5
C29: Wall Fan | E29: 10 | F29: unit | G29: 2000 | H29: =E29*G29 -> 20000 | K29: =E29 -> 10
C30: Industrial fan | E30: 3 | F30: unit | G30: 6000 | H30: =E30*G30 -> 18000 | K30: =E30 -> 3
C31: Airconditioning Unit, 2HP, Window-Type | E31: 4 | F31: unit | G31: 35000 | H31: =E31*G31 -> 140000 | K31: =E31 -> 4
C32: Airconditioning Unit, Floor mounted, 3TR | E32: 2 | F32: unit | G32: 120000 | H32: =E32*G32 -> 240000 | K32: =E32 -> 2
C33: Power Spray for cleaning and washing | E33: 2 | F33: unit | G33: 8000 | H33: =E33*G33 -> 16000 | K33: =E33 -> 2
C35: For use of Batangas Provincial Hospital | G35: =SUM(H36:H41) -> 517600 | I35: BIDDING/SHOPPING/ SMALL VALUE
C36: Dryer | D36: Industrial Type, 9 kg | E36: 1 | F36: unit | G36: 59000 | H36: =E36*G36 -> 59000 | K36: =E36 -> 1
C37: Fire Extinguisher | D37: 10 lbs | E37: 19 | F37: unit | G37: 9000 | H37: =E37*G37 -> 171000 | K37: =E37 -> 19
C38: Fire Extinguisher | D38: 50 lbs | E38: 5 | F38: unit | G38: 20000 | H38: =E38*G38 -> 100000 | K38: =E38 -> 5
C39: Floor Polisher | D39: Industrial Type, Wet and Dry | E39: 1 | F39: unit | G39: 50600 | H39: =E39*G39 -> 50600 | K39: =E39 -> 1
C40: Food Conveyor | D40: With Trays, 2-doors, stainless, 30 trays capacity | E40: 1 | F40: unit | G40: 85000 | H40: =E40*G40 -> 85000 | K40: =E40 -> 1
C41: Sound System | E41: 1 | F41: unit | G41: 52000 | H41: =E41*G41 -> 52000 | K41: =E41 -> 1
C43: For use of Calatagan Medicare Hospital | G43: =SUM(H44:H46) -> 170000 | I43: BIDDING/SHOPPING/ SMALL VALUE
C44: Nebulizer Pulmo Aide | E44: 5 | F44: unit | G44: 15000 | H44: =E44*G44 -> 75000 | K44: =E44 -> 5
C45: BP Aneroid APG Adult | E45: 10 | F45: unit | G45: 2000 | H45: =E45*G45 -> 20000 | K45: =E45 -> 10
C46: BP Aneroid With Wheels | E46: 5 | F46: unit | G46: 15000 | H46: =E46*G46 -> 75000 | K46: =E46 -> 5
C47: Pulse Oximeter Fingertip | E47: 10 | F47: unit | G47: 3000 | H47: =E47*G47 -> 30000 | K47: =E47 -> 10
C48: Oxygen Regulator W/ Accessories | E48: 10 | F48: unit | G48: 2500 | H48: =E48*G48 -> 25000 | K48: =E48 -> 10
C50: For use of Don Manuel Lopez Memorial District Hospital | F50: 520K | I50: BIDDING/SHOPPING/ SMALL VALUE
C52: For use of Dr. Ernesto H. Malabanan Memorial District Hospital | F52: 152K | I52: BIDDING/SHOPPING/ SMALL VALUE
C54: For use of Laurel Memorial District Hospital | G54: =SUM(H55:H57) -> 206200 | I54: BIDDING/SHOPPING/ SMALL VALUE
C55: Grass Cutter | D55: for grounds | E55: 5 | F55: unit | G55: 9000 | H55: =E55*G55 -> 45000 | K55: =E55 -> 5
C56: Floor Polisher | D56: Industrial Type, Wet and Dry | E56: 2 | F56: unit | G56: 50600 | H56: =E56*G56 -> 101200 | K56: =E56 -> 2
C57: Steamer | D57: for laundry | E57: 1 | F57: unit | G57: 60000 | H57: =E57*G57 -> 60000 | K57: =E57 -> 1
C59: For use of Lobo Municipal Hospital | G59: =SUM(H60:H66) -> 143000 | I59: BIDDING/SHOPPING/ SMALL VALUE
C60: Wall Fan | E60: 9 | F60: unit | G60: 2000 | H60: =E60*G60 -> 18000 | K60: =E60 -> 9
C61: Industrial fan | E61: 5 | F61: unit | G61: 6000 | H61: =E61*G61 -> 30000 | K61: =E61 -> 5
C62: Steel Cabinet | D62: (4-layer) | E62: 1 | F62: unit | G62: 15000 | H62: =E62*G62 -> 15000 | K62: =E62 -> 1
C63: Dish Sterilizer | D63: HDS 88 CUFT | E63: 1 | F63: unit | G63: 30000 | H63: =E63*G63 -> 30000 | K63: =E63 -> 1
C64: Electric Dish Dryer | E64: 1 | F64: unit | G64: 15000 | H64: =E64*G64 -> 15000 | K64: =E64 -> 1
C65: Airconditioning Unit | D65: 1.5 HP Window Type (Inverter) | E65: 1 | F65: unit | G65: 35000 | H65: =E65*G65 -> 35000 | K65: =E65 -> 1
C67: For use of Martin Marasigan District Hospital | F67: 256k | I67: BIDDING/SHOPPING/ SMALL VALUE
C69: For use of MVM Sto. Rosario Memorial District Hospital | F69: 304k | I69: BIDDING/SHOPPING/ SMALL VALUE
C71: For use of San Jose District Hospital | F71: 520k | I71: BIDDING/SHOPPING/ SMALL VALUE
C73: For use of San Juan District Hospital | G73: =SUM(H74:H77) -> 255000 | I73: BIDDING/SHOPPING/ SMALL VALUE
C74: Washing Machine | D74: Heavy Duty, Automatic | E74: 1 | F74: unit | G74: 75000 | H74: =E74*G74 -> 75000 | K74: =E74 -> 1
C75: Ceiling Fan | E75: 18 | F75: unit | G75: 3000 | H75: =E75*G75 -> 54000 | K75: =E75 -> 18
C76: Airconditioning Unit | D76: 1.5 HP Window Type (Inverter) | E76: 2 | F76: unit | G76: 35000 | H76: =E76*G76 -> 70000 | K76: =E76 -> 2
C77: Refrigerator | D77: 2-Door, Inverter | E77: 1 | F77: unit | G77: 56000 | H77: =E77*G77 -> 56000 | K77: =E77 -> 1
C79: Total | H79: =SUM(H26:H78) -> 1865800
A81: 10705020 | C81: OFFICE EQUIPMENT | H81: 5000000 | I81: BIDDING/SHOPPING/ SMALL VALUE
B82: 1 | C82: Airconditioning Unit | D82: 2 HP Window Type (Inverter) | E82: 42 | F82: unit | G82: 50000 | H82: =E82*G82 -> 2100000
B83: 2 | C83: Airconditioning Unit | D83: 2 HP Split Type (Inverter) | E83: 24 | F83: unit | G83: 55000 | H83: =E83*G83 -> 1320000
B84: 3 | C84: Airconditioning Unit | D84: 3 HP Window Type (Inverter) | E84: 2 | F84: unit | G84: 65000 | H84: =E84*G84 -> 130000
B85: 4 | C85: Airconditioning Unit | D85: Floor mounted, 3TR | E85: 2 | F85: unit | G85: 120000 | H85: =E85*G85 -> 240000
B86: 5 | C86: Steel Cabinet | D86: With open shelves | E86: 5 | F86: unit | G86: 150000 | H86: =E86*G86 -> 750000
B87: 6 | C87: Duplicator Machine | E87: 1 | F87: unit | G87: 100000 | H87: =E87*G87 -> 100000
B88: 7 | C88: Photocopier Machine | E88: 1 | F88: unit | G88: 75000 | H88: =E88*G88 -> 75000
B89: 8 | C89: Queuing Machine | E89: 1 | F89: unit | G89: 50000 | H89: =E89*G89 -> 50000
C91: Total | H91: =SUM(H82:H90) -> 4765000
C92: For use of PHO-Proper | G92: =SUM(H93:H94) -> 330000 | I92: BIDDING/SHOPPING/ SMALL VALUE
C93: Airconditioning Unit | D93: 1.5 HP Window Type (Inverter) | E93: 3 | F93: unit | G93: 35000 | H93: =E93*G93 -> 105000 | K93: =E93 -> 3
C94: Airconditioning Unit | D94: 1.5 HP Split Type (Inverter) | E94: 5 | F94: unit | G94: 45000 | H94: =E94*G94 -> 225000 | K94: =E94 -> 5
C96: For use of Provincial Health Care Facility | G96: =SUM(H97:H100) -> #VALUE! | I96: BIDDING/SHOPPING/ SMALL VALUE
C97: 4 Gang Seater | D97: Stainless | E97: 2 | F97: unit | G97: ₱ 15,138.00 | H97: =E97*G97 -> #VALUE! | K97: =E97 -> 2
C98: Filing Cabinet | D98: Steel 4-Drawer Vertical | E98: 1 | F98: unit | G98: ₱ 20,178.00 | H98: =E98*G98 -> #VALUE! | K98: =E98 -> 1
C99: Office Chair | D99: with Arm Rest | E99: 1 | F99: unit | G99: ₱ 9,684.00 | H99: =E99*G99 -> #VALUE! | K99: =E99 -> 1
C100: Filing Cabinet | D100: Glass with lock | E100: 1 | F100: unit | G100: ₱ 21,798.00 | H100: =E100*G100 -> #VALUE! | K100: =E100 -> 1
C102: For use of Apacible Memorial District Hospital | G102: =SUM(H103:H110) -> 780000 | I102: BIDDING/SHOPPING/ SMALL VALUE
C103: Computer Chair | E103: 11 | F103: unit | G103: 4000 | H103: =E103*G103 -> 44000 | K103: =E103 -> 11
C104: Executive Chair | E104: 5 | F104: unit | G104: 8000 | H104: =E104*G104 -> 40000 | K104: =E104 -> 5
C105: Office Table | E105: 10 | F105: unit | G105: 4500 | H105: =E105*G105 -> 45000 | K105: =E105 -> 10
C106: Office Chair | E106: 10 | F106: unit | G106: 5000 | H106: =E106*G106 -> 50000 | K106: =E106 -> 10
C107: Steel Cabinet | D107: With open shelves | E107: 3 | F107: unit | G107: 150000 | H107: =E107*G107 -> 450000 | K107: =E107 -> 3
C108: Steel Rack Shelves | D108: 5-layers Boltless, 1.2 meters | E108: 10 | F108: unit | G108: 5800 | H108: =E108*G108 -> 58000 | K108: =E108 -> 10
C109: Data Cabinet | D109: 4U 600mm x 450mm Cabinet with lock, wall mountable | E109: 11 | F109: unit | G109: 3000 | H109: =E109*G109 -> 33000 | K109: =E109 -> 11
C110: Filing Cabinets with Vault | D110: 4-Layers | E110: 5 | F110: unit | G110: 12000 | H110: =E110*G110 -> 60000 | K110: =E110 -> 5
C112: For use of Batangas Provincial Hospital | G112: =SUM(H113:H117) -> 780000 | I112: BIDDING/SHOPPING/ SMALL VALUE
C113: Duplicator Machine | E113: 1 | F113: unit | G113: 100000 | H113: =E113*G113 -> 100000 | K113: =E113 -> 1
C114: Photocopier Machine | E114: 1 | F114: unit | G114: 75000 | H114: =E114*G114 -> 75000 | K114: =E114 -> 1
C115: Queuing Machine | E115: 1 | F115: unit | G115: 30000 | H115: =E115*G115 -> 30000 | K115: =E115 -> 1
C116: Airconditioning Unit | D116: 1.5 HP Split Type (Inverter) | E116: 5 | F116: unit | G116: 45000 | H116: =E116*G116 -> 225000 | K116: =E116 -> 5
C117: Airconditioning Unit | D117: 1.5 HP Window Type (Inverter) | E117: 10 | F117: unit | G117: 35000 | H117: =E117*G117 -> 350000 | K117: =E117 -> 10
C119: For use of Calatagan Medicare Hospital | G119: =SUM(H120:H121) -> 370000 | I119: BIDDING/SHOPPING/ SMALL VALUE
C120: Storage Rack | D120: Boltless Shelving, 5 Layers, Heavy Duty, Large (1200x400mm) | E120: 20 | F120: unit | G120: 5000 | H120: =E120*G120 -> 100000 | K120: =E120 -> 20
C121: Airconditioning Unit | D121: 1.5 HP Split Type (Inverter) | E121: 6 | F121: unit | G121: 45000 | H121: =E121*G121 -> 270000 | K121: =E121 -> 6
C123: For use of Don Manuel Lopez Memorial District Hospital | G123: =SUM(H124:H131) -> 780000 | I123: BIDDING/SHOPPING/ SMALL VALUE
...

Sheet NUTRITION DEVT FUND
A1: Republic of the Philippines Provincial Government of Batangas PROVINCIAL HEALTH OFFICE Brgy. Kumintang Ibaba, Batangas City E-mail: pho@batangas.gov.ph | Tel No. (043) 740-2832; (043) 723-2592
A2: PROJECT PROCUREMENT MANAGEMENT PLAN 2026
A3: END USER/UNIT: | C3: PROVINCIAL HEALTH OFFICE - PROPER
A4: CHARGED TO: | C4: NUTRITION DEVELOPMENT PROGRAM
A6: CODE | B6: GENERAL DESCRIPTION | D6: QTY | E6: UNIT | F6: UNIT PRICE | G6: ESTIMATED BUDGET | H6: MODE OF PROCUREMENT | I6: SCHEDULE / MILESTONE OF ACTIVITIES
I7: JAN | J7: FEB | K7: MAR | L7: APR | M7: MAY | N7: JUN | O7: JUL | P7: AUG | Q7: SEP | R7: OCT | S7: NOV | T7: DEC
C8: MAINTENANCE AND OTHER OPERATING EXPENSES
A10: 50202010 | C10: TRAINING EXPENSES | G10: 600000 | H10: BIDDING/SMALL VALUE
C11: Registration Fee (Attendance to Seminars, Trainings, Conventions, etc) | I11: x | J11: x | K11: x | L11: x | M11: x | N11: x | O11: x | P11: x | Q11: x | R11: x | S11: x | T11: x
C12: Meals and Snacks of Participants | I12: x | J12: x | K12: x | L12: x | M12: x | N12: x | O12: x | P12: x | Q12: x | R12: x | S12: x | T12: x
C13: Honorarium of Resource Speakers, Lecturers and Trainors | I13: x | J13: x | K13: x | L13: x | M13: x | N13: x | O13: x | P13: x | Q13: x | R13: x | S13: x | T13: x
C14: Total | G14: =G10 -> 600000
A17: 50203010 | C17: OFFICE SUPPLIES EXPENSES | G17: 250000 | H17: BIDDING/SMALL VALUE
B18: 1 | C18: Ballpen, black, 12's/box | D18: 50 | E18: box | F18: 110.5 | G18: =D18*F18 -> 5525 | L18: 25 | P18: 25
B19: 2 | C19: Battery, AA by 4's / pack | D19: 10 | E19: pack | F19: 148 | G19: =D19*F19 -> 1480 | L19: 5 | P19: 5
B20: 3 | C20: Battery, AAA by 4's / pack | D20: 10 | E20: pack | F20: 302 | G20: =D20*F20 -> 3020 | L20: 5 | P20: 5
B21: 4 | C21: Board paper, 220 gsm, Short, White, 10piece / pack | D21: 60 | E21: pack | F21: 75 | G21: =D21*F21 -> 4500 | L21: 30 | P21: 30
B22: 5 | C22: Bond paper, white,long, 80 gsm, 24 substance | D22: 70 | E22: ream | F22: 498 | G22: =D22*F22 -> 34860 | L22: 35 | P22: 35
B23: 6 | C23: Calculator, 12 digit | D23: 50 | E23: piece | F23: 670 | G23: =D23*F23 -> 33500 | L23: 25 | P23: 25
B24: 7 | C24: Certificate Holder, 8.5" x 11" | D24: 300 | E24: piece | F24: 65 | G24: =D24*F24 -> 19500 | L24: 150 | P24: 150
B25: 8 | C25: Correction Tape, 150 meters | D25: 30 | E25: piece | F25: 60 | G25: =D25*F25 -> 1800 | L25: 15 | P25: 15
B26: 9 | C26: Printer ink 003, continuous, Black | D26: 30 | E26: piece | F26: 373 | G26: =D26*F26 -> 11190 | L26: 15 | P26: 15
B27: 10 | C27: Printer ink 003, continuous, Cyan | D27: 12 | E27: piece | F27: 381 | G27: =D27*F27 -> 4572 | L27: 6 | P27: 6
B28: 11 | C28: Printer ink 003, continuous, Magenta | D28: 12 | E28: piece | F28: 381 | G28: =D28*F28 -> 4572 | L28: 6 | P28: 6
B29: 12 | C29: Printer ink 003, continuous, Yellow | D29: 12 | E29: piece | F29: 381 | G29: =D29*F29 -> 4572 | L29: 6 | P29: 6
... B54: 37 | C54: Transparent Tape, 1" | D54: 15 | E54: piece | F54: 39 | G54: =D54*F54 -> 585 | L54: 7 | P54: 8
B55: 38 | C55: Scissors, stainless | D55: 5 | E55: piece | F55: 178 | G55: =D55*F55 -> 890 | P55: 5
B56: 39 | C56: Stapler #10, heavy duty | D56: 5 | E56: piece | F56: 478.5 | G56: =D56*F56 -> 2392.5 | P56: 5
B57: 40 | C57: Staple Wire, no. 35, (5000 piece./box) | D57: 9 | E57: box | F57: 80 | G57: =D57*F57 -> 720 | L57: 5 | P57: 4
C58: Total | G58: =SUM(G18:G57) -> 249991
A61: 50203070 | C61: DRUGS AND MEDICINE EXPENSES | G61: 1200000 | H61: BIDDING/SMALL VALUE
B62: 1 | C62: Iron + Folic Acid, 60 mg/400 mcg, film coated, 100's/box | D62: 3580 | E62: box | F62: 300 | G62: =D62*F62 -> 1074000 | J62: =D62 -> 3580
B63: 2 | C63: Calcium Carbonate, 1.25g tablet with 500 mg. elemental calcium, 100's/box | D63: 252 | E63: box | F63: 500 | G63: =D63*F63 -> 126000 | J63: 252
C64: Total | G64: =SUM(G62:G63) -> 1200000
A67: 50203990 | C67: OTHER SUPPLIES AND MATERIALS EXPENSES | G67: 3000000
C68: Recognition and Awarding of Provincial Nutrition Champions | H68: BIDDING/SMALL VALUE
B69: 1 | C69: Plaque 12" | D69: 10 | E69: piece | F69: 5000 | G69: =D69*F69 -> 50000 | O69: 7 | S69: 3
B70: 2 | C70: Plaque 10" | D70: 10 | E70: piece | F70: 4000 | G70: =D70*F70 -> 40000 | O70: 7 | S70: 3
B71: 3 | C71: Plaque 8" | D71: 7 | E71: piece | F71: 3000 | G71: =D71*F71 -> 21000 | O71: 7
C73: Food Commodities for the Tutok Kainan supplementation Program | H73: BIDDING/SMALL VALUE
B74: 4 | C74: For the identified nutritionally at risk 6-23 months preschool children | D74: =SUM(I74:T74) -> 300 | E74: pack | F74: 5000 | G74: =D74*F74 -> 1500000 | O74: 300
B75: 5 | C75: For the identified nutritionally at risk pregnant women | D75: 300 | E75: pack | F75: 4000 | G75: =D75*F75 -> 1200000 | O75: 300
B77: 6 | C77: Tshirt with collar and print (sublimation) | D77: =SUM(I77:T77) -> 250 | E77: piece | F77: 750 | G77: =D77*F77 -> 187500 | N77: 250
B79: 7 | C79: Extension Cord, 3 gang , 5 meters, heavy duty | D79: =SUM(I79:T79) -> 1 | E79: piece | F79: 600 | G79: =D79*F79 -> 600 | L79: 1
C80: Total | G80: =SUM(G69:G79) -> 2999100
A83: 50206020 | C83: PRIZES | G83: 250000
C84: Cash Prize | I84: x | J84: x | K84: x | L84: x | M84: x | N84: x | O84: x | P84: x | Q84: x | R84: x | S84: x | T84: x
C85: Total | G85: =G83 -> 250000
A88: 50299020 | C88: PRINTING AND PUBLICATION EXPENSES | G88: 250000
B89: 1 | C89: Printing of Nutrition IEC Materials | I89: x | J89: x | K89: x | L89: x | M89: x | N89: x | O89: x | P89: x | Q89: x | R89: x | S89: x | T89: x
C90: Total | G90: 250000
A93: 50299080 | C93: DONATIONS | G93: 750000 | H93: BIDDING/SMALL VALUE
B94: 1 | C94: Nutri/Height Boards for Height and Length | D94: 45 | E94: piece | F94: 8000 | G94: =D94*F94 -> 360000 | N94: 45
C95: height : 5 ft (60 inches)
C96: weight : 5.27 kg
C97: width : 11.3 inches
C98: material : plyboard with edging
C99: with calibration sticker
B101: 2 | C101: Beam Balance Scale / Platform Scale | D101: 11 | E101: units | F101: 23000 | G101: =D101*F101 -> 253000 | N101: 11
C102: Capacity:400 lb x 4 oz , 180 kg x 100 g, 400 lb x 4 oz / 175 kg x 100 g
C103: Scale Height:59 in / 150 cm
C104: Height Rod (on select models - 2392 excluded):30 to 78 in / 76 to 200 cm - 1/4 in / 1/2 cm increments
C105: Platform Size:10.5 in W x 14.5 in D / 27 cm W x 37 cm D
B107: 3 | C107: Test Weights
C108: Set composed of 10 piece TWR-10/MI/SC - Rectangular Test Weight 10 kg Class MI Cast iron with Box | D108: =SUM(I108:T108) -> 5 | E108: set | F108: 2795 | G108: =D108*F108 -> 13975 | L108: 5
C109: Set composed of 5 piece TWR-5/MI/B - Rectangular Test Weight 5 kg Class MI Cast iron with Box | D109: =SUM(I109:T109) -> 5 | E109: set | F109: 1716 | G109: =D109*F109 -> 8580 | L109: 5
B111: 4 | C111: Steel Rule
C112: Fuji Steel Rule, 150 cm | D112: =SUM(I112:T112) -> 4 | E112: piece | F112: 5590 | G112: =D112*F112 -> 22360 | L112: 4
B114: 5 | C114: Pabasa Bida Kit set | D114: 46 | E114: set | F114: 2000 | G114: =D114*F114 -> 92000 | N114: 46
C115: Total | G115: =SUM(G94:G114) -> 749915
A117: 50299990 | C117: OTHER MAINTENANCE AND OPERATING EXPENSES | F117: 1000000 | G117: 100000
C118: Accomodation | I118: x | J118: x | K118: x | L118: x | M118: x | N118: x | O118: x | P118: x | Q118: x | R118: x | S118: x | T118: x
C119: Honorarium of Speakers, Lecturers and Trainers | I119: x | J119: x | K119: x | L119: x | M119: x | N119: x | O119: x | P119: x | Q119: x | R119: x | S119: x | T119: x
C120: Total | F120: =F117 -> 1000000 | G120: =G117 -> 100000
D121: GRAND TOTAL | G121: =SUM(G120,G115,G90,G85,G80,G64,G58,G14,) -> 6399006
A123: Prepared by: | D123: Recommending Approval: | N123: Approved by:
A127: CYNTHIA E. LACABA | D127: GERALD G. ALDAY, MD., MPA., FPSMSI | N127: HON. VILMA SANTOS RECTO
A128: Nutrition Officer IV | D128: OIC - Provincial Health Officer | N128: Provincial Governor

Sheet TB ELIMINATION SERVICES
A1: Republic of the Philippines Provincial Government of Batangas PROVINCIAL HEALTH OFFICE Brgy. Kumintang Ibaba, Batangas City E-mail: pho@batangas.gov.ph | Tel No. (043) 740-2832; (043) 723-2592
A2: PROJECT PROCUREMENT MANAGEMENT PLAN 2026
A3: END USER/UNIT: | C3: PROVINCIAL HEALTH OFFICE
A4: CHARGED TO: | C4: TUBERCULOSIS ELIMINATION PROGRAM
A6: CODE | B6: GENERAL DESCRIPTION | E6: QTY | F6: UNIT | G6: UNIT PRICE | H6: ESTIMATED BUDGET | I6: MODE OF PROCUREMENT | J6: SCHEDULE / MILESTONE OF ACTIVITIES
J7: JAN | K7: FEB | L7: MAR | M7: APR | N7: MAY | O7: JUN | P7: JUL | Q7: AUG | R7: SEP | S7: OCT | T7: NOV | U7: DEC
C8: MAINTENANCE AND OTHER OPERATING EXPENSES
A10: 50202010 | C10: TRAINING EXPENSES | H10: 200000 | I10: BIDDING/SMALL VALUE | J10: x | K10: x | L10: x | M10: x | N10: x | O10: x | P10: x | Q10: x | R10: x | S10: x | T10: x | U10: x
C11: Meals and snacks
C12: Registration Fee
C13: Food and Accomodation
C14: Total | H14: =H10 -> 200000
A16: 50203010 | C16: OFFICE SUPPLIES EXPENSES | H16: 51000 | I16: BIDDING/SMALL VALUE
B17: 1 | C17: Epson L3110 - 003 Black | E17: 13 | F17: bottle | G17: =1000 -> 1000 | H17: =E17*G17 -> 13000 | L17: 13
B18: 2 | C18: Epson L3110 - 003 Yellow | E18: 11 | F18: bottle | G18: 1100 | H18: =E18*G18 -> 12100 | L18: 11
B19: 3 | C19: Epson L3110 - 003 Magenta | E19: 11 | F19: bottle | G19: 1100 | H19: =E19*G19 -> 12100 | L19: 11
B20: 4 | C20: Epson L3110 - 003 Cyan | E20: 11 | F20: bottle | G20: 1100 | H20: =E20*G20 -> 12100 | L20: 11
C21: Total | H21: =SUM(H17:H20) -> 49300
A23: 50203070 | C23: DRUGS AND MEDICINES EXPENSES | H23: 1500000 | I23: BIDDING/SMALL VALUE
B24: 1 | C24: Purified Protein Derivative (PPD), 5TU/.1mL solution / 1ml | E24: 1000 | F24: vial | H24: 500000 | L24: 1000
C25: Anti-TB Drugs for Children
C26: (7 bottles) Rifampicin 200mg/5mL, 120mL
C27: (4 bottles) Pyrazinamide 250mg/5mL, 120mL
C28: (7 bottles) Isoniazid 200mg/5mL, 120mL
B29: 2 | C29: Intensive Phase Anti TB Drugs for Adult: | E29: 210 | F29: box | H29: 411600 | L29: 210
C30: Fixed Dose Combination 4 80's/box
C31: (Rifampicin 150mg, Isoniazid75 mg, Pyrazinamide 400mg,
C32: Ethambutol 275 mg)
B33: 3 | C33: Maintenance Phase Anti TB Drugs for Adult: | E33: 420 | F33: box | H33: 588400 | L33: 420
C34: Fixed Dose Combination 2 80's/box
C35: (Rifampicin 150mg, Isoniazid75 mg)
C36: Total | H36: =SUM(H24:H35) -> 1500000
A38: 50203080 | C38: MEDICAL, DENTAL, & LABORATORY SUPPLIES EXPENSES | H38: 500000 | I38: BIDDING/SMALL VALUE
B39: 1 | C39: BD Insulin Syringe with needle-0.05ml, 100's/box | E39: 273 | F39: box | G39: 1500 | H39: =E39*G39 -> 409500 | L39: 480
B40: 2 | C40: Sputum cup, with red screw cup cover 60ml | E40: 2033 | F40: piece | G40: 15 | H40: =E40*G40 -> 30495 | L40: 2075
B41: 3 | C41: Staining Reagent, Ziehl-Neelsen (AFB Staining) | E41: 15 | F41: kit | G41: 4000 | H41: =E41*G41 -> 60000 | L41: 15
C42: Total | H42: =SUM(H39:H41) -> 499995
A44: 50206020 | C44: PRIZES | H44: 100000
B45: 1 | C45: Advocacy on TB Prevention and Control LUNG MONTH CELEBRATION | J45: x | K45: x | L45: x | M45: x | N45: x | O45: x | P45: x | Q45: x | R45: x | S45: x | T45: x | U45: x
C46: Cash Prizes for TB Program Top Performers
C47: Total | H47: =H44 -> 100000
A49: 50299020 | C49: PRINTING AND PUBLICATION EXPENSES | H49: 150000 | I49: BIDDING/SMALL VALUE | J49: x | K49: x | L49: x | M49: x | N49: x | O49: x | P49: x | Q49: x | R49: x | S49: x | T49: x | U49: x
B50: 1 | C50: Leaflets/ pamphlets
B51: 2 | C51: Manuals, Hard bond, Soft bond
B52: 3 | C52: Posters
B53: 4 | C53: Treatment Cards, ID Cards
B54: 5 | C54: TB Register
B55: 6 | C55: Laboratory Register
C56: Total | H56: =H49 -> 150000
A58: 50299990 | C58: OTHER MAINTENANCE AND OPERATING EXPENSES | H58: 50000
B59: 1 | C59: Honorarium for TBMAC | J59: x | K59: x | L59: x | M59: x | N59: x | O59: x | P59: x | Q59: x | R59: x | S59: x | T59: x | U59: x
B60: 2 | C60: Honorarium for Guest | J60: x | K60: x | L60: x | M60: x | N60: x | O60: x | P60: x | Q60: x | R60: x | S60: x | T60: x | U60: x
B61: 3 | C61: Speakers/Lectures/Trainors | J61: x | K61: x | L61: x | M61: x | N61: x | O61: x | P61: x | Q61: x | R61: x | S61: x | T61: x | U61: x
B62: 4 | C62: Honorarium for Medical Specialist | J62: x | K62: x | L62: x | M62: x | N62: x | O62: x | P62: x | Q62: x | R62: x | S62: x | T62: x | U62: x
C63: Total | H63: =H58 -> 50000
C65: CAPITAL OUTLAY
A67: 10705030 | C67: INFORMATION AND COMMUNICATION TECHNOLOGY EQUIPMENT | H67: 150000 | I67: BIDDING/SMALL VALUE
B68: 1 | C68: Projector | E68: 2 | F68: unit | G68: 75000 | H68: =E68*G68 -> 150000 | Q68: 1
C69: Total | H69: =SUM(H68) -> 150000
E70: GRAND TOTAL | H70: =SUM(H69,H63,H56,H47,H42,H36,H21,H14,) -> 2699295
A74: Prepared by: | E74: Recommending Approval: | O74: Approved by:
A78: VIVIAN B. HERNANDEZ | E78: GERALD G. ALDAY, MD., MPA., FPSMSI | O78: HON. VILMA SANTOS RECTO
A79: Nurse V | E79: OIC - Provincial Health Officer | O79: Provincial Governor

Sheet HSFES
A1: Republic of the Philippines Provincial Government of Batangas PROVINCIAL HEALTH OFFICE Brgy. Kumintang Ibaba, Batangas City E-mail: pho@batangas.gov.ph | Tel No. (043) 740-2832; (043) 723-2592
A2: PROJECT PROCUREMENT MANAGEMENT PLAN 2026
A3: END USER/UNIT: | C3: PROVINCIAL HEALTH OFFICE
A4: CHARGED TO: | C4: HEALTH SERVICES AND FACILITIES ENHANCEMENT SERVICES
A6: CODE | B6: GENERAL DESCRIPTION | E6: QTY | F6: UNIT | G6: UNIT PRICE | H6: ESTIMATED BUDGET | I6: MODE OF PROCUREMENT | J6: SCHEDULE / MILESTONE OF ACTIVITIES
J7: JAN | K7: FEB | L7: MAR | M7: APR | N7: MAY | O7: JUN | P7: JUL | Q7: AUG | R7: SEP | S7: OCT | T7: NOV | U7: DEC
C8: MAINTENANCE AND OTHER OPERATING EXPENSES
A10: 50202010 | C10: TRAINING EXPENSES | H10: 700000 | I10: BIDDING/SMALL VALUE | J10: x | K10: x | L10: x | M10: x | N10: x | O10: x | P10: x | Q10: x | R10: x | S10: x | T10: x | U10: x
C11: Meals and Accomodation/ Food and Venue
C12: Training Materials
C14: Total | H14: 700000
A16: 50203070 | C16: DRUGS AND MEDICINE EXPENSES | H16: 2500000
C18: Senior and Persons with Disabilities (PWD) Program | I18: BIDDING/SMALL VALUE
C19: Anti Flu Vaccine | E19: 200 | F19: vial | G19: 1000 | H19: =E19*G19 -> 200000 | K19: 200
C20: Anti Pneumonia Vaccine | E20: 150 | F20: vial | G20: 2000 | H20: =E20*G20 -> 300000 | K20: 150
C23: Rabies Prevention and Control Program | I23: BIDDING/SMALL VALUE
C24: Anti-Rabies Vaccine | E24: 440 | F24: vials | G24: 3600 | H24: =E24*G24 -> 1584000 | K24: 440
C25: Erig Vaccine - Equirab | E25: 200 | F25: vials | G25: 2000 | H25: =E25*G25 -> 400000 | K25: 200
C26: Tetanus Toxoid 0.5ml ampule by 10s | E26: 150 | F26: vials | G26: 100 | H26: =E26*G26 -> 15000 | K26: 150
C27: Total | H27: =SUM(H19:H26) -> 2499000
A29: 50203080 | C29: MEDICAL, DENTAL, AND LABORATORY SUPPLIES EXPENSES | H29: 2500000
C30: Volunteer Blood Services Program | I30: BIDDING/SMALL VALUE
C31: Hemoglobin Analyzer Microcuvette | E31: 2 | F31: box | G31: =12500*1.4 -> 17500 | H31: =E31*G31 -> 35000 | K31: 2
C32: Typing Sera | D32: 10 ml (Anti-A, Anti-B, Anti-D) | E32: 20 | F32: set | G32: =(30000/20)*1.4 -> 2100 | H32: =E32*G32 -> 42000 | K32: =E32 -> 20
C34: Non-communicable Disease Program | I34: BIDDING/SMALL VALUE
C35: ECG Paper | D35: 110mmx20m | E35: 75 | F35: roll | G35: 560 | H35: =E35*G35 -> 42000 | K35: =E35 -> 75
C36: Glass Slides | D36: 72 | E36: 7 | F36: box | G36: 150 | H36: =E36*G36 -> 1050 | K36: =E36 -> 7
C37: Cotton Applicator | D37: 100's | E37: 5 | F37: box | G37: 250 | H37: =E37*G37 -> 1250 | K37: =E37 -> 5
C38: Bleaching solution | D38: 1 gallon | E38: 1 | F38: gallon | G38: 200 | H38: =E38*G38 -> 200 | K38: =E38 -> 1
C39: Surgical Gloves | D39: sterile, size 6 | E39: 1 | F39: box | G39: 100 | H39: =E39*G39 -> 100 | K39: =E39 -> 1
C40: Surgical Gloves | D40: sterile, size 7 | E40: 1 | F40: box | G40: 100 | H40: =E40*G40 -> 100 | K40: =E40 -> 1
C41: Surgical Gloves | D41: sterile, size 8 | E41: 1 | F41: box | G41: 100 | H41: =E41*G41 -> 100 | K41: =E41 -> 1
C44: Senior and Persons with Disabilities (PWD) Program | I44: BIDDING/SMALL VALUE
C45: Wheel Chair | D45: for adult, heavy duty | E45: 12 | F45: piece | G45: 6000 | H45: =E45*G45 -> 72000 | M45: 12
C46: Pediatric Wheel Chair | D46: heavy duty | E46: 12 | F46: piece | G46: 6000 | H46: =E46*G46 -> 72000 | M46: 12
C47: Quad Cane | D47: adjustable height, contoured handle, heavy duty | E47: 25 | F47: piece | G47: 1500 | H47: =E47*G47 -> 37500 | M47: 25
C48: Crutch Aid Medical Walker | D48: stainless steel, height adjustable | E48: 15 | F48: piece | G48: 2500 | H48: =E48*G48 -> 37500 | M48: 15
C49: Wellness Kit | D49: for seniors | E49: 25 | F49: kit | G49: 3500 | H49: =E49*G49 -> 87500 | M49: 25
C50: Contents per kit:
C51: -Storage box -Standard Pulse Oximeter, Large SPO2 and PR display with bar graph display, Multiple applications in hospital, home, community medical treatment and sports treatment, Accurate measurement of SPO2 and PR with storage and lanyard -2 boxes of Food and supplement syrup per Senior-12 Sachets of 15ml Syrup -Resistance Band (8-word latex resistance band elastic gym equipment) -Calming oil, oil soothes and relaxes 10 ml roll that stress away, 2 pcs. -Herbal Nasal Inhaler with essential oils (natural remedy for headache, sinus, fever and flu) 10 ml -Turmeric tea powder, 10-in-1 Turmeric Tea is composed of 10 different powerful herbs: Pandan, Sambong, Lagundi, Banaba, Ginger, Malunggay, Gynura Procumbens, Lemongrass, Peppermint and Turmeric, (400g pack) -Stevia, 100% Natural Zero Calorie Sweetener , Stevia Leaf Extract Sweetener, Erythritol Sweetener, Sugar Substitute, Sugar Free, Diabetes Friendly, Sugar Alternative, 100sticks/box -Moringa capsule, 500mg., good for 1month -Milk for Senior Citizen, 150 g
C52: DRRMH - Health Emergency Management System | I52: BIDDING/SMALL VALUE
C53: First Aid Kits | E53: 35 | F53: kit | G53: 2500 | H53: =E53*G53 -> 87500 | M53: 35
C54: Contents per kit: -1 pc. First Aid Bag -1 pc. Digital Thermometer -6 pcs. Alcohol swabs -1 pair Sterile Gloves -1 pc. Surgical Tape (1 inch) -50 pcs. Band Aid -5 pcs. Gauze Pads, 4x4 -5 pcs. Gauze Pads, 3x3 -1 pc. Cloth Triangular Bandage -1 pc. Instant Ice Pack -1 pc. Elastic Bandage, 2" -1 pc. Tweezer -1 pc. Scissor -2 pcs. Rolled Gauze, 2"x10y -1 bot. Povidone lodine -1 bot. Hydrogen Peroxide -1 pack Cotton Balls -20 tabs Paracetamol, 500 mg -1 bot. Spirit of Ammonia, 15ml -1 pc. Torniquet
C55: Wash Kits | E55: 125 | F55: kit | G55: 450 | H55: =E55*G55 -> 56250 | M55: 125
C56: Contents per kit: -15 pcs. Aquatabs -1 pc. Collapsible Water Container, 20L
C57: Hygiene Kits | E57: 100 | F57: kit | G57: 2000 | H57: =E57*G57 -> 200000 | M57: 100
C58: Contents per kit: -1 pc. Malong, XL size -1 pc. Toothpaste, 100 ml -4 pcs. Toothbrush -20 pcs. Facemasks -2 pcs. Face Towel -2 pcs. Bath Soap, 135g -2 bot. Alcohol, 100 ml -1 bar Detergent Soap -1 pc. Storage Box -1 pack Sanitary Napkin,8's -1 Hair Comb - 1 Nail Cutter
C60: HIV Program | I60: BIDDING/SMALL VALUE
C61: Determine HIV Early Detect 100's | E61: 10 | F61: box | G61: 23000 | H61: =E61*G61 -> 230000 | O61: 10
C62: HIV/Syphilis DUO 25's | E62: 25 | F62: box | G62: 8500 | H62: =E62*G62 -> 212500 | O62: 25
C63: Detemine HBsAg 2 100's | E63: 10 | F63: box | G63: 11000 | H63: =E63*G63 -> 110000 | O63: 10
C64: Gram Stain Kits | E64: 64 | F64: kits | G64: 7000 | H64: =E64*G64 -> 448000 | O64: 64
C66: Sexual and Reproductive Health | I66: BIDDING/SMALL VALUE
C67: Povidone-Iodine | D67: 7.5% Skin Cleanser | E67: 2 | F67: gallon | G67: 1500 | H67: =E67*G67 -> 3000 | K67: 2
C68: Sterilizing & disinfecting solution | E68: 2 | F68: gallon | G68: 700 | H68: =E68*G68 -> 1400 | K68: 2
C69: Surgical Gloves | D69: Sterile, Size 7, 50 pieces/box | E69: 2 | F69: box | G69: 100 | H69: =E69*G69 -> 200 | K69: 2
C70: Surgical Gloves | D70: Sterile, Size 7.5, 50 pieces/box | E70: 2 | F70: box | G70: 100 | H70: =E70*G70 -> 200 | K70: 2
C71: Surgical Gloves | D71: Sterile, Size 5.5, 50 pieces/box | E71: 2 | F71: box | G71: 100 | H71: =E71*G71 -> 200 | K71: 2
C72: Latex Examination Gloves | D72: Medium, 100 pieces/box | E72: 2 | F72: box | G72: 565 | H72: =E72*G72 -> 1130 | K72: 2
C73: Latex Examination Gloves | D73: Small, 100 pieces/box | E73: 2 | F73: box | G73: 565 | H73: =E73*G73 -> 1130 | K73: 2
C74: Latex Examination Gloves | D74: Large, 100 pieces/box | E74: 2 | F74: box | G74: 565 | H74: =E74*G74 -> 1130 | K74: 2
C75: Micropore Tape | D75: 1"x10 yd, 3M, US, 12 pieces/box | E75: 50 | F75: box | G75: =118*12 -> 1416 | H75: =E75*G75 -> 70800 | K75: 50
C76: Surgical Gauze | D76: Square Pack 12x12 | E76: 1 | F76: roll | G76: =159*1.4 -> 222.6 | H76: =E76*G76 -> 222.6 | K76: 1
C77: Cotton Balls | D77: 1000 pcs/pack | E77: 5 | F77: pack | G77: 300 | H77: =E77*G77 -> 1500 | K77: 5
C78: Disposable Electrosurgical Pen | E78: 1 | F78: piece | G78: 500 | H78: =E78*G78 -> 500 | K78: 1
C79: Electrosurgical Grounding Pad | E79: 3 | F79: piece | G79: 800 | H79: =E79*G79 -> 2400 | K79: 3
C82: Water Analysis | I82: BIDDING/SMALL VALUE
C83: Vessel with Sodium Thiosulfate 120ml, 200 pieces per box | E83: 2 | F83: box | G83: 35000 | H83: =E83*G83 -> 70000 | K83: 2
C84: Autoclave Tape 1'' | E84: 5 | F84: piece | G84: 1064 | H84: =E84*G84 -> 5320 | K84: 5
C85: Automatic Pipette Stand | E85: 1 | F85: unit | G85: 600 | H85: =E85*G85 -> 600 | K85: 1
C86: Borosilicate Glass Separatory Funnel with stopper, 700mL | E86: 1 | F86: piece | G86: 11200 | H86: =E86*G86 -> 11200 | K86: 1
C87: Borosilicate Glass Stirring Rod 300mm | E87: 2 | F87: piece | G87: 840 | H87: =E87*G87 -> 1680 | K87: 2
C88: Denatured Alcohol1L | E88: 5 | F88: bottle | G88: 2100 | H88: =E88*G88 -> 10500 | K88: 5
C89: Distilled Water6 liters | E89: 60 | F89: bottle | G89: 350 | H89: =E89*G89 -> 21000 | K89: 60
C90: Doormat Medium Cotton | E90: 6 | F90: piece | G90: 140 | H90: =E90*G90 -> 840 | K90: 6
C91: Examining Gloves Medium | E91: 8 | F91: box | G91: 565 | H91: =E91*G91 -> 4520 | K91: 8
C92: Examining Gloves Small | E92: 7 | F92: box | G92: 565 | H92: =E92*G92 -> 3955 | K92: 7
C93: Fermentation Tube/Test Tube70mm x 10mm , 50 pieces per box/pack | E93: 4 | F93: box | G93: 11200 | H93: =E93*G93 -> 44800 | K93: 4
C94: Liquid Hand Wash/Hand Soap250ml | E94: 5 | F94: piece | G94: 210 | H94: =E94*G94 -> 1050 | K94: 5
... C104: Yellow Tips 1000's, Universal | E104: 5 | F104: pack | G104: 420 | H104: =E104*G104 -> 2100 | K104: 5
C105: Total | H105: =SUM(H31:H104) -> 2455983.6
A107: 50203130 | C107: CHEMICAL AND FILTERING SUPPLIES | H107: 500000 | I107: BIDDING/SMALL VALUE
C108: Chlorine Granules, 70%, 1kg/jar | E108: 30 | F108: jar | H108: 18000 | K108: 30
C109: Chlorine, 40 kgs Chlorine, 40 kgs | E109: 10 | F109: container | H109: 192000 | K109: 10
C110: Troclosene Sodium | E110: 35 | F110: box | H110: 48720 | K110: 35
C111: Disinfectant Sterilizing Solution, gallon | E111: 50 | F111: gal | H111: 56450 | K111: 50
C112: Lime - 40 kilos/sack | E112: 5 | F112: sack | H112: 11400 | K112: 5
C113: Disinfection Spray | E113: 50 | F113: can | H113: 14487 | K113: 50
C114: Freeze Dried Bacteria 12.5 kg | E114: 1 | F114: pail | H114: 65000 | K114: 1
C115: Liquid Enzyme 20 Liters | E115: 1 | F115: pail | H115: 45000 | K115: 1
C116: Liquid Chlorine | E116: 600 | F116: liter | H116: 43056 | K116: 600
C117: Total | H117: =SUM(H108:H116) -> 494113
A120: 50211030 | C120: CONSULTANCY SERVICES | H120: 150000 | J120: x | K120: x | L120: x | M120: x | N120: x | O120: x | P120: x | Q120: x | R120: x | S120: x | T120: x | U120: x
C121: DOH and DENR Compliance of District Hospitals
C122: Total | H122: =H120 -> 150000
A124: 50212010 | C124: ENVIRONMENTAL AND SANITARY SERVICES | H124: 14000000 | I124: BIDDING/SMALL VALUE
C125: Pathological and Hospital Waste | J125: x | K125: x | L125: x | M125: x | N125: x | O125: x | P125: x | Q125: x | R125: x | S125: x | T125: x | U125: x
C126: Siphoning | J126: x | K126: x | L126: x | M126: x | N126: x | O126: x | P126: x | Q126: x | R126: x | S126: x | T126: x | U126: x
C127: Repair of STP | J127: x | K127: x | L127: x | M127: x | N127: x | O127: x | P127: x | Q127: x | R127: x | S127: x | T127: x | U127: x
C128: Maintenance of Sewage Treatment Plant including Maintenance of Septic Tank | J128: x | K128: x | L128: x | M128: x | N128: x | O128: x | P128: x | Q128: x | R128: x | S128: x | T128: x | U128: x
...

Sheet PHO-PROPER FUND
A1: Republic of the Philippines Provincial Government of Batangas PROVINCIAL HEALTH OFFICE Brgy. Kumintang Ibaba, Batangas City E-mail: pho@batangas.gov.ph | Tel No. (043) 740-2832; (043) 723-2592
A2: PROJECT PROCUREMENT MANAGEMENT PLAN 2025
A3: END USER/UNIT: | C3: PROVINCIAL HEALTH OFFICE - PROPER
A4: CHARGED TO: | C4: GENERAL FUND - PHO-PROPER
A6: CODE | B6: GENERAL DESCRIPTION | E6: QTY | F6: UNIT | G6: UNIT PRICE | H6: ESTIMATED BUDGET | I6: MODE OF PROCUREMENT | J6: SCHEDULE / MILESTONE OF ACTIVITIES
J7: JAN | K7: FEB | L7: MAR | M7: APR | N7: MAY | O7: JUN | P7: JUL | Q7: AUG | R7: SEP | S7: OCT | T7: NOV | U7: DEC
C8: MAINTENANCE AND OTHER OPERATING EXPENSES
A10: 50201010 | C10: TRAVELING EXPENSES - LOCAL | G10: 0 | H10: 1200000
A12: ='Cover Page'!A10 -> 50203020 | C12: ACCOUNTABLE FORMS EXPENSES | H12: 10000 | I12: BIDDING/SHOPPING/ SMALL VALUE
A14: ='Cover Page'!A11 -> 50203030 | C14: NON-ACCOUNTABLE FORMS EXPENSES | H14: 475000 | I14: BIDDING/SHOPPING/ SMALL VALUE
A16: ='Cover Page'!A14 -> 50203090 | C16: FUEL, OIL AND LUBRICANTS EXPENSES | H16: 3500000 | I16: BIDDING/SHOPPING/ SMALL VALUE
A18: 50205020 | C18: TELEPHONE EXPENSES | H18: 316000
A20: 50205030 | C20: INTERNET SUBSCRIPTION EXPENSES | H20: 300000
A22: 50205040 | C22: CABLE, SATELLITE, TELEGRAPH AND RADIO EXPENSES | H22: 20000 | I22: SHOPPING
A24: ='Cover Page'!A19 -> 50206020 | C24: PRIZES | H24: 210000 | I24: BIDDING/SHOPPING/ SMALL VALUE
C26: REPAIRS AND MAINTENANCE
A27: ='Cover Page'!A20 -> 50213040 | C27: BUILDING AND OTHER STRUCTURES | H27: 3200000 | I27: BIDDING/SHOPPING/ SMALL VALUE
A29: ='Cover Page'!A10 -> 50203020 | C29: MACHINERY AND EQUIPMENT | H29: 400000 | I29: BIDDING/SHOPPING/ SMALL VALUE
A31: ='Cover Page'!A11 -> 50203030 | C31: TRANSPORTATION EQUIPMENT | H31: 750000 | I31: BIDDING/SHOPPING/ SMALL VALUE
A33: 50216010 | C33: TAXES, DUTIES, AND LICENSES | H33: 25000
A35: 50216020 | C35: FIDELITY BOND PREMIUMS | H35: 100000
A37: 50299030 | C37: PRINTING AND PUBLICATION EXPENSES | H37: 250000 | I37: BIDDING/SHOPPING/ SMALL VALUE
A39: 50299040 | C39: TRANSPORTATION & DELIVERY EXPENSES | H39: 260000 | I39: BIDDING/SHOPPING/ SMALL VALUE
A40: 50299050 | C40: RENT EXPENSES | H40: 750000 | I40: BIDDING/SHOPPING/ SMALL VALUE
A42: ='Cover Page'!A8 -> 50202010 | C42: TRAINING EXPENSES | H42: 250000 | I42: BIDDING/SHOPPING/ SMALL VALUE
C43: Meals and Accomodation/ Food and Venue | E43: =#REF! -> #REF! | F43: pax | G43: =H43/E43 -> #REF! | H43: =#REF! -> #REF! | K43: 350 | P43: 250
C44: Others | H44: 250000
C45: Registration Fee
C46: Total | H46: =SUM(H43:H44) -> #REF!
A48: 50203010 | C48: OFFICE SUPPLIES EXPENSES | H48: 3000000
C49: For use of PHO-Proper | I49: BIDDING/SHOPPING/ SMALL VALUE
C50: All Purpose Sticker | D50: A4 10's/pack | E50: 100 | F50: pack | G50: 77 | H50: =E50*G50 -> 7700 | K50: =E50/2 -> 50 | P50: =E50/2 -> 50
C51: AntiVirus Software | D51: With 2 years License | E51: 2 | F51: piece | G51: 4000 | H51: =E51*G51 -> 8000 | K51: =E51 -> 2 | P51: =E51/2 -> 1
C52: Arch File | D52: Vertical, 2-Ring Binder, 2" Side, Long, Black | E52: 50 | F52: piece | G52: 200 | H52: =E52*G52 -> 10000
C53: Arch File | D53: Vertical, 2-Ring Binder, 2" Side, A4, Black | E53: 30 | F53: piece | G53: 200 | H53: =E53*G53 -> 6000
C54: Ballpen | D54: Black 0.5mm | E54: 220 | F54: piece | G54: 15 | H54: =E54*G54 -> 3300 | O54: 60 | P54: 50 | Q54: 50
C55: Ballpen | D55: Black 0.7mm | E55: 1200 | F55: piece | G55: 11.2 | H55: =E55*G55 -> 13440 | K55: =E55/2 -> 600 | P55: =E55/2 -> 600
C56: Ballpen | D56: Blue 0.7mm | E56: 1200 | F56: piece | G56: 11.2 | H56: =E56*G56 -> 13440 | K56: =E56/2 -> 600 | P56: =E56/2 -> 600
C57: Ballpen | D57: Red 0.7mm | E57: 1200 | F57: piece | G57: 11.2 | H57: =E57*G57 -> 13440 | K57: =E57/2 -> 600 | P57: =E57/2 -> 600
C58: Battery | D58: AA (4piece/pack) | E58: 100 | F58: pack | G58: 191.8 | H58: =E58*G58 -> 19180 | K58: =E58/2 -> 50 | P58: =E58/2 -> 50
C59: Battery | D59: AAA (4piece/pack) | E59: 100 | F59: pack | G59: 229.25 | H59: =E59*G59 -> 22925 | K59: =E59/2 -> 50 | P59: =E59/2 -> 50
C60: Battery | D60: AA (4piece/pack) Rechargeable with charger | E60: 100 | F60: pack | G60: 1141 | H60: =E60*G60 -> 114100 | K60: =E60/2 -> 50 | P60: =E60/2 -> 50
C61: Battery | D61: AAA(4piece/pack) Rechargeable with charger | E61: 100 | F61: pack | G61: 1159.2 | H61: =E61*G61 -> 115920 | K61: =E61/2 -> 50 | P61: =E61/2 -> 50
C62: Binder clip | D62: 2 in 12 piece per box | E62: 10 | F62: box | G62: 84 | H62: =E62*G62 -> 840 | K62: =E62/2 -> 5 | P62: =E62/2 -> 5
C63: Binder clip | D63: 3/4 12 piece per box | E63: 10 | F63: box | G63: 134.4 | H63: =E63*G63 -> 1344 | K63: =E63/2 -> 5 | P63: =E63/2 -> 5
C64: Binder clip | D64: 1 5/8 12 piece per box | E64: 10 | F64: box | G64: 67.2 | H64: =E64*G64 -> 672 | K64: =E64/2 -> 5 | P64: =E64/2 -> 5
C65: Binder clip | D65: 1 1/4 12 piece per box | E65: 10 | F65: box | G65: 100.8 | H65: =E65*G65 -> 1008 | K65: =E65/2 -> 5 | P65: =E65/2 -> 5
C66: Colored Paper | D66: 100 piece/pack | E66: 60 | F66: pack | G66: =300*1.4 -> 420 | H66: =E66*G66 -> 25200 | K66: =E66/2 -> 30 | P66: =E66/2 -> 30
C67: Bond Paper White | D67: Short 80 gsm / 24 substance | E67: 450 | F67: ream | G67: 438.2 | H67: =E67*G67 -> 197190 | K67: =E67/2 -> 225 | P67: =E67/2 -> 225
C68: Bond Paper White | D68: Long 80 gsm / 24 substance | E68: 450 | F68: ream | G68: 575.4 | H68: =E68*G68 -> 258930 | K68: =E68/2 -> 225 | P68: =E68/2 -> 225
C69: Bond Paper White | D69: A4 80 gsm / 24 substance | E69: 450 | F69: ream | G69: 506.8 | H69: =E69*G69 -> 228060 | K69: =E69/2 -> 225 | P69: =E69/2 -> 225
C70: Bond Paper White | D70: Extra Long 70 gsm / 20 substance | E70: 10 | F70: ream | G70: 575.4 | H70: =E70*G70 -> 5754 | K70: =E70/2 -> 5 | P70: =E70/2 -> 5
C71: Brown Envelope | D71: Short 150LBS | E71: 600 | F71: piece | G71: 6 | H71: =E71*G71 -> 3600 | K71: =E71/2 -> 300 | P71: =E71/2 -> 300
C72: Brown Envelope | D72: Long 150LBS | E72: 1000 | F72: piece | G72: 7 | H72: =E72*G72 -> 7000 | K72: =E72/2 -> 500 | P72: =E72/2 -> 500
C73: Bundy Clock | D73: E2A | E73: 2 | F73: unit | G73: 22000 | H73: =E73*G73 -> 44000 | K73: =E73/2 -> 1 | P73: =E73/2 -> 1
C74: Bundy Clock Ribbon | D74: E2A | E74: 5 | F74: piece | G74: 1260 | H74: =E74*G74 -> 6300 | K74: 3 | P74: =E74-K74 -> 2
C75: Calculator | D75: 12 digits (Heavy Duty) | E75: 12 | F75: piece | G75: 812.5 | H75: =E75*G75 -> 9750 | K75: =E75/2 -> 6 | P75: =E75/2 -> 6
C76: Carbon Paper | D76: Long 100s/pack blue/black | E76: 2 | F76: pack | G76: 1036 | H76: =E76*G76 -> 2072 | K76: =E76/2 -> 1 | P76: =E76/2 -> 1
C77: Cartolina | D77: Assorted Color (20 pieces/pack) | E77: 40 | F77: pack | G77: 100 | H77: =E77*G77 -> 4000 | K77: 3 | P77: =E77-K77 -> 37
C78: Clear Book | D78: Short (100 page) | E78: 30 | F78: piece | G78: 225.75 | H78: =E78*G78 -> 6772.5 | K78: =E78/2 -> 15 | P78: =E78/2 -> 15
C79: Clear Book | D79: Long (100 page) | E79: 50 | F79: piece | G79: 323.75 | H79: =E79*G79 -> 16187.5 | K79: =E79/2 -> 25 | P79: =E79/2 -> 25
C80: Clip Board | D80: Short | E80: 15 | F80: piece | G80: 103.75 | H80: =E80*G80 -> 1556.25 | K80: 8 | P80: =E80-K80 -> 7
C81: Clip Board | D81: Long | E81: 30 | F81: piece | G81: 107.5 | H81: =E81*G81 -> 3225 | K81: =E81/2 -> 15 | P81: =E81/2 -> 15
C82: Clip Board | D82: Short with cover | E82: 15 | F82: piece | G82: 135.8 | H82: =E82*G82 -> 2037 | K82: 8 | P82: 7
C83: Clip Board | D83: Long with cover | E83: 30 | F83: piece | G83: 140 | H83: =E83*G83 -> 4200 | K83: =E83/2 -> 15 | P83: =E83/2 -> 15
C84: Columnar Book | D84: No. 707 | E84: 5 | F84: piece | G84: 86.25 | H84: =E84*G84 -> 431.25 | K84: 3 | P84: =E84-K84 -> 2
C85: Compact Disc | D85: Re-writable with case | E85: 20 | F85: piece | G85: 100.8 | H85: =E85*G85 -> 2016 | K85: =E85/2 -> 10 | P85: =E85/2 -> 10
C86: Computer Keyboard | D86: Wired (USB connection) | E86: 3 | F86: unit | G86: 1000 | H86: =E86*G86 -> 3000 | K86: 2 | P86: =E86-K86 -> 1
C87: Computer Keyboard | D87: Wireless | E87: 3 | F87: unit | G87: 1925 | H87: =E87*G87 -> 5775 | K87: 2 | P87: =E87-K87 -> 1
C88: Computer Mouse | D88: Wireless | E88: 5 | F88: unit | G88: 945 | H88: =E88*G88 -> 4725 | K88: 3 | P88: =E88-K88 -> 2
C89: Computer Set with printer (Intel Core i5, 8GB DDR, 1TB Hard Disk, LED Monitor, Wired Key board, Mouse,Windows 11, 3-in-1 printer) | E89: 2 | F89: set | G89: 100000 | H89: =E89*G89 -> 200000 | K89: =E89 -> 2
C90: Cord | D90: Nylon Fancy Yarn | E90: 10 | F90: roll | G90: 210 | H90: =E90*G90 -> 2100 | K90: =E90/2 -> 5 | P90: =E90/2 -> 5
C91: Cork Board | D91: With aluminum frame 11''x16'' | E91: 2 | F91: piece | G91: 350 | H91: =E91*G91 -> 700 | K91: =E91/2 -> 1 | P91: =E91/2 -> 1
C92: Cork Board | D92: With aluminum frame 12"x12" | E92: 2 | F92: piece | G92: 167.5 | H92: =E92*G92 -> 335 | K92: =E92/2 -> 1 | P92: =E92/2 -> 1
C93: Correction Tape | D93: 150 meters | E93: 150 | F93: piece | G93: 50 | H93: =E93*G93 -> 7500 | K93: =E93/2 -> 75 | P93: =E93/2 -> 75
C94: Cutter | D94: Big (Heavy Duty) | E94: 10 | F94: piece | G94: 90 | H94: =E94*G94 -> 900 | K94: =E94/2 -> 5 | P94: =E94/2 -> 5
C95: Dater Stamp | D95: Month/Day/Year format | E95: 5 | F95: piece | G95: 1200 | H95: =E95*G95 -> 6000 | K95: 3 | P95: =E95-K95 -> 2
C96: Desk Organizer | D96: 3 layer mesh metal tray | E96: 5 | F96: piece | G96: 308 | H96: =E96*G96 -> 1540 | K96: 3 | P96: =E96-K96 -> 2
C97: Desk Organizer | D97: With Mesh File Holder, Heavy Duty | E97: 5 | F97: piece | G97: 3500 | H97: =E97*G97 -> 17500 | K97: 3 | P97: =E97-K97 -> 2
C98: Double Adhesive Tape | D98: 1'' | E98: 20 | F98: roll | G98: 39.2 | H98: =E98*G98 -> 784 | K98: =E98/2 -> 10 | P98: =E98/2 -> 10
C99: Double Adhesive Tape | D99: 2'' | E99: 20 | F99: roll | G99: 70 | H99: =E99*G99 -> 1400 | K99: =E99/2 -> 10 | P99: =E99/2 -> 10
C100: Duplicator Machine Master Roll | D100: DP-G325 | E100: 10 | F100: roll | G100: 8242.5 | H100: =E100*G100 -> 82425 | K100: =E100/2 -> 5 | P100: =E100/2 -> 5
C101: Duplicator Machine Master Roll | D101: CV/B4 UA | E101: 10 | F101: roll | G101: 8242.5 | H101: =E101*G101 -> 82425 | K101: =E101/2 -> 5 | P101: =E101/2 -> 5
C102: Duplicator Machine Toner | D102: Black Ink (DP-G325) | E102: 20 | F102: piece | G102: 11795 | H102: =E102*G102 -> 235900 | K102: =E102/2 -> 10 | P102: =E102/2 -> 10
C103: Eraser | D103: Rubber (medium) | E103: 10 | F103: piece | G103: 30 | H103: =E103*G103 -> 300 | K103: =E103/2 -> 5 | P103: =E103/2 -> 5
C104: Expanded Folder | D104: Long (green) | E104: 50 | F104: piece | G104: 22.4 | H104: =E104*G104 -> 1120 | K104: =E104/2 -> 25 | P104: =E104/2 -> 25
C105: External Hard drive | D105: 1 TB | E105: 5 | F105: piece | G105: 6608 | H105: =E105*G105 -> 33040 | K105: 3 | P105: =E105-K105 -> 2
C106: Fastener | D106: Metal (50sets/box) | E106: 30 | F106: box | G106: 123.75 | H106: =E106*G106 -> 3712.5 | K106: =E106/2 -> 15 | P106: =E106/2 -> 15
C107: Fastener | D107: Plastic (50sets/box) | E107: 10 | F107: box | G107: 107.5 | H107: =E107*G107 -> 1075 | K107: =E107/2 -> 5 | P107: =E107/2 -> 5
C108: Filing Tray | D108: 3 layers (Metal) | E108: 10 | F108: piece | G108: 658 | H108: =E108*G108 -> 6580 | K108: =E108/2 -> 5 | P108: =E108/2 -> 5
C109: Flash Drive | D109: 128GB | E109: 30 | F109: piece | G109: 2142 | H109: =E109*G109 -> 64260 | K109: =E109/2 -> 15 | P109: =E109/2 -> 15
C110: Duplicator Machine Toner | D110: Black Ink (CV-3230) | E110: 30 | F110: roll | G110: 11795 | H110: =E110*G110 -> 353850 | K110: =E110/2 -> 15 | P110: =E110/2 -> 15
C111: Folder | D111: Short (white) | E111: 100 | F111: piece | G111: 15 | H111: =E111*G111 -> 1500 | K111: =E111/2 -> 50 | P111: =E111/2 -> 50
C112: Folder | D112: Long (white) | E112: 500 | F112: piece | G112: 15 | H112: =E112*G112 -> 7500 | K112: =E112/2 -> 250 | P112: =E112/2 -> 250
C113: Folder | D113: Expandable Long | E113: 100 | F113: piece | G113: 42 | H113: =E113*G113 -> 4200 | K113: =E113/2 -> 50 | P113: =E113/2 -> 50
C114: Folder | D114: Pressboard Long(green) | E114: 100 | F114: piece | G114: 36 | H114: =E114*G114 -> 3600 | K114: =E114/2 -> 50 | P114: =E114/2 -> 50
C115: Gel Pen | D115: Eraseable, 0.4mm Black 12 pieces/box | E115: 10 | F115: box | G115: 100 | H115: =E115*G115 -> 1000 | K115: =E115/2 -> 5 | P115: =E115/2 -> 5
C116: Glue | D116: All Purpose 60 ml | E116: 20 | F116: piece | G116: 50.4 | H116: =E116*G116 -> 1008 | K116: =E116/2 -> 10 | P116: =E116/2 -> 10
C117: Glue Gun | D117: Heavy Duty | E117: 5 | F117: piece | G117: 387.8 | H117: =E117*G117 -> 1939 | K117: 3 | P117: =E117-K117 -> 2
C118: Highliter Pen | D118: Assorted Color (4piece/pack) | E118: 50 | F118: pack | G118: 210 | H118: =E118*G118 -> 10500 | K118: =E118/2 -> 25 | P118: =E118/2 -> 25
...
